**第一课第一题**

**题目：**

自己写一个简单的 Hello.java，里面需要涉及基本类型，四则运行，if 和
for，然后自己分析一下对应的字节码

**源代码：**

```java
package com.example.demo.jvm;

public class Hello {
    private char charField;
    private int intField;
    private float floatField;
    long longField;
    public double doubleField;
    public boolean booleanField;

    public Hello(char charField, int intField, float floatField, long longField, double doubleField, boolean booleanField) {
        this.charField = charField;
        this.intField = intField;
        this.floatField = floatField;
        this.longField = longField;
        this.doubleField = doubleField;
        this.booleanField = booleanField;
    }

    public static void showIfElse(boolean flag) {
        if (flag) {
            System.out.println("true......");
        } else {
            System.out.println("false......");
        }
    }

    public void loop(int number) {
        long result = 1;
        for (int i = 0; i < number; i++) {
            result *= number;
        }
        System.out.println(result);
    }


    private int add(int a, int b) {
        return a + b;
    }

    public double sub(double a, float b) {
        return a - b;
    }

    public double multiply(double a, int b) {
        return a * b;
    }

    public double divide(double a, double b) {
        if (b != 0) {
            return a / b;
        }
        throw new RuntimeException("divisor can not be zero");
    }

}
```



**通过javap -v -p Hello.class反汇编之后的汇编指令， javap默认不显示private修饰的方法和字段，加上-p之后显示**

```
Classfile /D:/project/demo/src/main/java/com/example/demo/jvm/Hello.class
  Last modified 2021-1-8; size 1636 bytes
  MD5 checksum 7365cac7539cd8fa01390a15c0edfb9a
  Compiled from "Hello.java" //编译来源
public class com.example.demo.jvm.Hello
  minor version: 0
  major version: 52 //表示编译的jdk版本号，52代表java8
  flags: ACC_PUBLIC, ACC_SUPER //类的访问权限修饰符，该类由public修饰
  //以下这一长串都是常量池， 包含字面量和符号引用，字面量包括final修饰是常量， 被""引起来的字符串， 基本数据类型的值， 
  //符号引用包含类的全限定名；字段和方法的名称和描述符
Constant pool:
   #1 = Methodref          #17.#58        // java/lang/Object."<init>":()V
   #2 = Fieldref           #16.#59        // com/example/demo/jvm/Hello.charField:C //表示该字段的符号引用， C是字段描述符
   #3 = Fieldref           #16.#60        // com/example/demo/jvm/Hello.intField:I
   #4 = Fieldref           #16.#61        // com/example/demo/jvm/Hello.floatField:F
   #5 = Fieldref           #16.#62        // com/example/demo/jvm/Hello.longField:J
   #6 = Fieldref           #16.#63        // com/example/demo/jvm/Hello.doubleField:D
   #7 = Fieldref           #16.#64        // com/example/demo/jvm/Hello.booleanField:Z
   #8 = Fieldref           #65.#66        // java/lang/System.out:Ljava/io/PrintStream;
   #9 = String             #67            // true......  //字符串的字面量
  #10 = Methodref          #68.#69        // java/io/PrintStream.println:(Ljava/lang/String;)V //方法的符号引用，(Ljava/lang/String;)V表示无返回值，参数是String对象
  #11 = String             #70            // false......
  #12 = Methodref          #68.#71        // java/io/PrintStream.println:(J)V
  #13 = Class              #72            // java/lang/RuntimeException
  #14 = String             #73            // divisor can not be zero
  #15 = Methodref          #13.#74        // java/lang/RuntimeException."<init>":(Ljava/lang/String;)V
  #16 = Class              #75            // com/example/demo/jvm/Hello
  #17 = Class              #76            // java/lang/Object
  #18 = Utf8               charField
  #19 = Utf8               C
  #20 = Utf8               intField
  #21 = Utf8               I
  #22 = Utf8               floatField
  #23 = Utf8               F
  #24 = Utf8               longField
  #25 = Utf8               J
  #26 = Utf8               doubleField
  #27 = Utf8               D
  #28 = Utf8               booleanField
  #29 = Utf8               Z
  #30 = Utf8               <init>
  #31 = Utf8               (CIFJDZ)V
  #32 = Utf8               Code
  #33 = Utf8               LineNumberTable
  #34 = Utf8               LocalVariableTable
  #35 = Utf8               this
  #36 = Utf8               Lcom/example/demo/jvm/Hello;
  #37 = Utf8               showIfElse
  #38 = Utf8               (Z)V
  #39 = Utf8               flag
  #40 = Utf8               StackMapTable
  #41 = Utf8               loop
  #42 = Utf8               (I)V
  #43 = Utf8               i
  #44 = Utf8               number
  #45 = Utf8               result
  #46 = Utf8               add
  #47 = Utf8               (II)I
  #48 = Utf8               a
  #49 = Utf8               b
  #50 = Utf8               sub
  #51 = Utf8               (DF)D
  #52 = Utf8               multiply
  #53 = Utf8               (DI)D
  #54 = Utf8               divide
  #55 = Utf8               (DD)D
  #56 = Utf8               SourceFile
  #57 = Utf8               Hello.java
  #58 = NameAndType        #30:#77        // "<init>":()V
  #59 = NameAndType        #18:#19        // charField:C
  #60 = NameAndType        #20:#21        // intField:I
  #61 = NameAndType        #22:#23        // floatField:F
  #62 = NameAndType        #24:#25        // longField:J
  #63 = NameAndType        #26:#27        // doubleField:D
  #64 = NameAndType        #28:#29        // booleanField:Z
  #65 = Class              #78            // java/lang/System
  #66 = NameAndType        #79:#80        // out:Ljava/io/PrintStream;
  #67 = Utf8               true......
  #68 = Class              #81            // java/io/PrintStream
  #69 = NameAndType        #82:#83        // println:(Ljava/lang/String;)V
  #70 = Utf8               false......
  #71 = NameAndType        #82:#84        // println:(J)V
  #72 = Utf8               java/lang/RuntimeException
  #73 = Utf8               divisor can not be zero
  #74 = NameAndType        #30:#83        // "<init>":(Ljava/lang/String;)V
  #75 = Utf8               com/example/demo/jvm/Hello
  #76 = Utf8               java/lang/Object
  #77 = Utf8               ()V
  #78 = Utf8               java/lang/System
  #79 = Utf8               out
  #80 = Utf8               Ljava/io/PrintStream;
  #81 = Utf8               java/io/PrintStream
  #82 = Utf8               println
  #83 = Utf8               (Ljava/lang/String;)V
  #84 = Utf8               (J)V
  
{
   private char charField;
    descriptor: C //字段描述符
    flags: ACC_PRIVATE //访问控制标识

  private int intField;
    descriptor: I
    flags: ACC_PRIVATE

  private float floatField;
    descriptor: F
    flags: ACC_PRIVATE

  long longField;
    descriptor: J
    flags:

  public double doubleField;
    descriptor: D
    flags: ACC_PUBLIC

  public boolean booleanField;
    descriptor: Z
    flags: ACC_PUBLIC
    //以上是字段信息数据区

//以下是方法信息数据区
//带参数的构造方法
  public com.example.demo.jvm.Hello(char, int, float, long, double, boolean);
    descriptor: (CIFJDZ)V  //参数类型是char， int， float， long， double， boolean， 没有返回值
    flags: ACC_PUBLIC		//访问权限标识符为public
    Code:
      stack=3, locals=9, args_size=7  //栈的长度为3， 本地变量有9个， 参数长度为7
         0: aload_0	//将0号槽位的局部变量加载到栈
         1: invokespecial #1                  // Method java/lang/Object."<init>":()V //调用常量池中的<init>方法
         4: aload_0           
         5: iload_1				//加载1号槽位的int类型局部变量到栈
         6: putfield      #2                  // Field charField:C  //为字段赋值， 以下的类似
         9: aload_0
        10: iload_2
        11: putfield      #3                  // Field intField:I
        14: aload_0
        15: fload_3
        16: putfield      #4                  // Field floatField:F
        19: aload_0
        20: lload         4
        22: putfield      #5                  // Field longField:J
        25: aload_0
        26: dload         6
        28: putfield      #6                  // Field doubleField:D
        31: aload_0
        32: iload         8
        34: putfield      #7                  // Field booleanField:Z
        37: return
      LineNumberTable: //描述字节码和源代码的对应关系
        line 11: 0
        line 12: 4
        line 13: 9
        line 14: 14
        line 15: 19
        line 16: 25
        line 17: 31
        line 18: 37
      LocalVariableTable: //本地变量表，展示了槽位的使用以及本地变量的作用域
        Start  Length  Slot  Name   Signature
            0      38     0  this   Lcom/example/demo/jvm/Hello; 
            0      38     1 charField   C
            0      38     2 intField   I
            0      38     3 floatField   F
            0      38     4 longField   J
            0      38     6 doubleField   D
            0      38     8 booleanField   Z
            
            
//静态方法ifelse
  public static void showIfElse(boolean);
    descriptor: (Z)V //参数是booolean类型， 没有返回值
    flags: ACC_PUBLIC, ACC_STATIC	//访问标识为public和static
    Code:
      stack=2, locals=1, args_size=1
         0: iload_0
         1: ifeq          15     //判断是否相等， 相等顺序执行， 不相等跳转到15行执行
         4: getstatic     #8                  // Field java/lang/System.out:Ljava/io/PrintStream; //访问静态类字段  
         7: ldc           #9                  // String true......  //将常量加载到操作数栈
         9: invokevirtual #10                 // Method java/io/PrintStream.println:(Ljava/lang/String;)V //调用方法
        12: goto          23				//goto跳转指令，直接返回
        15: getstatic     #8                  // Field java/lang/System.out:Ljava/io/PrintStream;
        18: ldc           #11                 // String false......
        20: invokevirtual #10                 // Method java/io/PrintStream.println:(Ljava/lang/String;)V
        23: return
      LineNumberTable:
        line 21: 0
        line 22: 4
        line 24: 15
        line 26: 23
      LocalVariableTable:
        Start  Length  Slot  Name   Signature
            0      24     0  flag   Z
      StackMapTable: number_of_entries = 2   //辅助类加载时的验证
        frame_type = 15 /* same */
        frame_type = 7 /* same */
        
        
//循环方法        
   public void loop(int);
    descriptor: (I)V
    flags: ACC_PUBLIC
    Code:
      stack=4, locals=5, args_size=2
         0: lconst_1   //加载常量1到操作数栈
         1: lstore_2	//将操作数栈上的值存放在本地变量表2中
         2: iconst_0    //加载常量0到操作数栈
         3: istore        4  //将操作数栈上的值存放在本地变量表4中
         5: iload         4  //把本地变量表4上的值放在操作数栈中
         7: iload_1
         8: if_icmpge     22 //比较指令， 相等继续执行， 不相等跳到22行执行
        11: lload_2			//从本地变量表中加载到栈
        12: iload_1	
        13: i2l			//类型转换，int to long
        14: lmul		//将栈上的两个数相乘
        15: lstore_2	//将栈上的数存储在本地变量表中
        16: iinc          4, 1 //本地变量表4位置上的变量自加1
        19: goto          5		//跳转到5行继续
        22: getstatic     #8                 // Field java/lang/System.out:Ljava/io/PrintStream; //获取静态变量， 在26行调用方法
        25: lload_2
        26: invokevirtual #12                 // Method java/io/PrintStream.println:(J)V
        29: return
      LineNumberTable:
        line 29: 0
        line 30: 2
        line 31: 11
        line 30: 16
        line 33: 22
        line 34: 29
      LocalVariableTable:
        Start  Length  Slot  Name   Signature
            5      17     4     i   I //槽位4存储的i这个变量
            0      30     0  this   Lcom/example/demo/jvm/Hello;
            0      30     1 number   I
            2      28     2 result   J
      StackMapTable: number_of_entries = 2
        frame_type = 253 /* append */
          offset_delta = 5
          locals = [ long, int ]
        frame_type = 250 /* chop */
          offset_delta = 16
          
 //add方法
  private int add(int, int);
    descriptor: (II)I
    flags: ACC_PRIVATE  //修饰符为私有
    Code:
      stack=2, locals=3, args_size=3
         0: iload_1  //把本地变量表中槽位1，2压栈， 然后把栈顶的值相加， 然后返回
         1: iload_2
         2: iadd
         3: ireturn
      LineNumberTable:
        line 38: 0
      LocalVariableTable:
        Start  Length  Slot  Name   Signature
            0       4     0  this   Lcom/example/demo/jvm/Hello;
            0       4     1     a   I
            0       4     2     b   I
            

//sub方法
  public double sub(double, float);
    descriptor: (DF)D
    flags: ACC_PUBLIC
    Code:
      stack=4, locals=4, args_size=3
         0: dload_1
         1: fload_3
         2: f2d		//float转换为double
         3: dsub	//做减法操作
         4: dreturn
      LineNumberTable:
        line 42: 0
      LocalVariableTable:
        Start  Length  Slot  Name   Signature
            0       5     0  this   Lcom/example/demo/jvm/Hello;
            0       5     1     a   D
            0       5     3     b   F
            
//multiply方法
  public double multiply(double, int);
    descriptor: (DI)D
    flags: ACC_PUBLIC
    Code:
      stack=4, locals=4, args_size=3
         0: dload_1
         1: iload_3
         2: i2d		//int 转换为double
         3: dmul	//做乘法操作
         4: dreturn
      LineNumberTable:
        line 46: 0
      LocalVariableTable:
        Start  Length  Slot  Name   Signature
            0       5     0  this   Lcom/example/demo/jvm/Hello;
            0       5     1     a   D
            0       5     3     b   I

//divide方法
  public double divide(double, double);
    descriptor: (DD)D
    flags: ACC_PUBLIC
    Code:
      stack=4, locals=5, args_size=3
         0: dload_3		//将3号槽位上的值压栈， 即b这个变量
         1: dconst_0	//将常量0压栈
         2: dcmpl		//比较0和b的值， 返回一个int类型的比较值， 所以即使代码中写了！， 这里还是相等继续执行， 否则跳转到抛出异常
         3: ifeq          10 //int类型的条件分支比较操作， 相等， 跳转到10执行， 不相等， 顺序执行
         6: dload_1
         7: dload_3
         8: ddiv			//做除法
         9: dreturn
        10: new           #13                 // class java/lang/RuntimeException	//创建一个该类的对象
        13: dup								//复制一份重新压入栈
        14: ldc           #14                 // String divisor can not be zero  //压入常量
        16: invokespecial #15                 // Method java/lang/RuntimeException."<init>":  (Ljava/lang/String;)V  //执行RuntimeException的<init>方法，初始化RuntimeException
        19: athrow		//抛出异常
      LineNumberTable:
        line 50: 0
        line 51: 6
        line 53: 10
      LocalVariableTable:
        Start  Length  Slot  Name   Signature
            0      20     0  this   Lcom/example/demo/jvm/Hello;
            0      20     1     a   D
            0      20     3     b   D
      StackMapTable: number_of_entries = 1
        frame_type = 10 /* same */
}
SourceFile: "Hello.java"   //源代码时Hello.java这个类
```

